isx/__init__.py
isx/_internal.py
isx/algo.py
isx/core.py
isx/io.py
isx/util.py
isx/lib/Qt5Core.dll
isx/lib/avcodec-57.dll
isx/lib/avformat-57.dll
isx/lib/avutil-55.dll
isx/lib/isxpublicapi.dll
isx/lib/isxpublicapi.exp
isx/lib/isxpublicapi.lib
isx/lib/swresample-2.dll
isx/test/__init__.py
isx/test/asserts.py
isx/test/test_algos.py
isx/test/test_core.py
isx/test/test_file_io.py
isx/test/test_file_metadata.py
isx/test/utilities/__init__.py
isx/test/utilities/create_sample_data.py
isx/test/utilities/setup.py
isx-2.1.0.dist-info/licenses/LICENSE.txt
isx-2.1.0.dist-info/METADATA
isx-2.1.0.dist-info/WHEEL
isx-2.1.0.dist-info/top_level.txt
isx-2.1.0.dist-info/RECORD
