Metadata-Version: 2.4
Name: isx
Version: 2.1.0
Summary: A python package for interacting with Inscopix data.
Home-page: https://github.com/inscopix/pyisx
Author: Inscopix, Inc.
Requires-Python: >=3.9,<3.14
License-File: LICENSE.txt
Requires-Dist: h5py>=2.8.0
Requires-Dist: numpy>=1.14
Requires-Dist: scipy>=1.0
Requires-Dist: tifffile>=0.15.1
Requires-Dist: pandas>=0.20.1
Requires-Dist: pillow>=8.0.1
Requires-Dist: openpyxl>=3.0.10
Provides-Extra: build
Requires-Dist: build; extra == "build"
Provides-Extra: test
Requires-Dist: pytest; extra == "test"
Provides-Extra: docs
Requires-Dist: sphinx; extra == "docs"
Requires-Dist: sphinx_rtd_theme; extra == "docs"
Requires-Dist: myst_parser; extra == "docs"
Provides-Extra: deploy
Requires-Dist: twine; extra == "deploy"
Dynamic: author
Dynamic: description
Dynamic: description-content-type
Dynamic: home-page
Dynamic: license-file
Dynamic: provides-extra
Dynamic: requires-dist
Dynamic: requires-python
Dynamic: summary
